django_phone_field-1.8.1.dist-info/METADATA
django_phone_field-1.8.1.dist-info/RECORD
django_phone_field-1.8.1.dist-info/WHEEL
django_phone_field-1.8.1.dist-info/top_level.txt
phone_field/__init__.py
phone_field/forms.py
phone_field/models.py
phone_field/phone_number.py
phone_field/templates/phone_field/phone_widget.html
phone_field/templatetags/__init__.py
phone_field/templatetags/phone.py
