Metadata-Version: 2.1
Name: django-phone-field
Version: 1.8.1
Summary: Lightweight model and form field for phone numbers in Django
Home-page: https://github.com/VeryApt/django-phone-field/
Author: Andrew Mackowski
Author-email: andrew@veryapt.com
Maintainer: Andrew Mackowski
Maintainer-email: andrew@veryapt.com
License: GPL
Keywords: django phonenumber phone number model field
Platform: OS Independent
Classifier: Intended Audience :: Developers
Classifier: License :: OSI Approved :: GNU General Public License v3 (GPLv3)
Classifier: Framework :: Django
Classifier: Programming Language :: Python
Classifier: Programming Language :: Python :: 3
Classifier: Programming Language :: Python :: 3.5
Classifier: Programming Language :: Python :: 3.6
Classifier: Programming Language :: Python :: 3.7
